chiral_client/__init__.py
chiral_client/app_type.py
chiral_client/client.py
chiral_client/ftp.py
chiral_client/types.py
chiral_client/apps/__init__.py
chiral_client/apps/gromacs.py
chiral_client/apps/llma2.py
chiral_client/apps/recgen.py
chiral_client/chiral/__init__.py
chiral_client/chiral/chiral_pb2.py
chiral_client/chiral/chiral_pb2.pyi
chiral_client/chiral/chiral_pb2_grpc.py
chiral_client-0.3.2.dist-info/LICENSE
chiral_client-0.3.2.dist-info/METADATA
chiral_client-0.3.2.dist-info/WHEEL
chiral_client-0.3.2.dist-info/top_level.txt
chiral_client-0.3.2.dist-info/RECORD
