Metadata-Version: 2.1
Name: chiral-client
Version: 0.3.2
Summary: Python Client for Chiral Computing Cloud
Home-page: https://github.com/chiral-data/chiral-client-python
Author: Qin Wan
Author-email: rogerwq@gmail.com
License: MIT
Classifier: Programming Language :: Python :: 3
Classifier: License :: OSI Approved :: MIT License
Classifier: Operating System :: OS Independent
License-File: LICENSE
